rosie-1.0.0.data/purelib/rosie/__init__.py
rosie-1.0.0.data/purelib/rosie/install_cli.py
rosie-1.0.0.data/purelib/rosie/librosie.dylib
rosie-1.0.0.data/purelib/rosie/rosie.py
rosie-1.0.0.data/purelib/rosie/rosie_cli
rosie-1.0.0.data/purelib/rosie/rosie-pattern-language/LICENSE
rosie-1.0.0.data/purelib/rosie/rosie-pattern-language/VERSION
rosie-1.0.0.data/purelib/rosie/rosie-pattern-language/lib/argparse.luac
rosie-1.0.0.data/purelib/rosie/rosie-pattern-language/lib/ast.luac
rosie-1.0.0.data/purelib/rosie/rosie-pattern-language/lib/boot.luac
rosie-1.0.0.data/purelib/rosie/rosie-pattern-language/lib/builtins.luac
rosie-1.0.0.data/purelib/rosie/rosie-pattern-language/lib/cli-common.luac
rosie-1.0.0.data/purelib/rosie/rosie-pattern-language/lib/cli-match.luac
rosie-1.0.0.data/purelib/rosie/rosie-pattern-language/lib/cli-parser.luac
rosie-1.0.0.data/purelib/rosie/rosie-pattern-language/lib/cli-test-command.luac
rosie-1.0.0.data/purelib/rosie/rosie-pattern-language/lib/cli.luac
rosie-1.0.0.data/purelib/rosie/rosie-pattern-language/lib/color.luac
rosie-1.0.0.data/purelib/rosie/rosie-pattern-language/lib/common.luac
rosie-1.0.0.data/purelib/rosie/rosie-pattern-language/lib/compile.luac
rosie-1.0.0.data/purelib/rosie/rosie-pattern-language/lib/engine_module.luac
rosie-1.0.0.data/purelib/rosie/rosie-pattern-language/lib/environment.luac
rosie-1.0.0.data/purelib/rosie/rosie-pattern-language/lib/expand.luac
rosie-1.0.0.data/purelib/rosie/rosie-pattern-language/lib/init.luac
rosie-1.0.0.data/purelib/rosie/rosie-pattern-language/lib/list.luac
rosie-1.0.0.data/purelib/rosie/rosie-pattern-language/lib/loadpkg.luac
rosie-1.0.0.data/purelib/rosie/rosie-pattern-language/lib/parse.luac
rosie-1.0.0.data/purelib/rosie/rosie-pattern-language/lib/parse_core.luac
rosie-1.0.0.data/purelib/rosie/rosie-pattern-language/lib/rcfile.luac
rosie-1.0.0.data/purelib/rosie/rosie-pattern-language/lib/recordtype.luac
rosie-1.0.0.dist-info/DESCRIPTION.rst
rosie-1.0.0.dist-info/LICENSE.txt
rosie-1.0.0.dist-info/METADATA
rosie-1.0.0.dist-info/RECORD
rosie-1.0.0.dist-info/WHEEL
rosie-1.0.0.dist-info/metadata.json
rosie-1.0.0.dist-info/top_level.txt
