Metadata-Version: 2.0
Name: rosie
Version: 1.0.0
Summary: Rosie Pattern Language (replaces regex for data mining and text search)
Home-page: http://rosie-lang.org
Author: Jamie Jennings
Author-email: rosie.pattern.language@gmail.com
License: MIT
Project-URL: Issue page, https://gitlab.com/rosie-pattern-language/rosie/issues
Project-URL: Documentation, https://gitlab.com/rosie-pattern-language/rosie/tree/master/doc
Project-URL: Source Code, https://gitlab.com/rosie-pattern-language
Keywords: rosie pattern language PEG regex regexp data mining text search
Platform: UNKNOWN
Classifier: Development Status :: 4 - Beta
Classifier: License :: OSI Approved :: MIT License
Classifier: Programming Language :: Python :: 2
Classifier: Programming Language :: Python :: 2.7
Classifier: Programming Language :: Python :: 3
Classifier: Programming Language :: Python :: 3.6
Classifier: Operating System :: POSIX :: Linux
Classifier: Operating System :: MacOS :: MacOS X
Classifier: Intended Audience :: Developers
Classifier: Intended Audience :: Science/Research
Classifier: Intended Audience :: System Administrators
Classifier: Topic :: Scientific/Engineering
Classifier: Topic :: Software Development :: Libraries
Classifier: Topic :: Text Processing :: General
Classifier: Topic :: Utilities
Requires-Dist: cffi (>=1.9)
